{
  "type": "FeatureCollection",
  "name": "土壤采样点模板",
  "description": "土壤调查采样点数据模板",
  "crs": {
    "type": "name",
    "properties": {
      "name": "EPSG:4326"
    }
  },
  "features": [
    {
      "type": "Feature",
      "properties": {
        "sample_id": "S001",
        "_field_descriptions": {
          "sample_id": {
            "名称": "采样点编号",
            "说明": "每个采样点的唯一标识符",
            "格式": "字符串，如 S001, S002",
            "必填": "是"
          },
          "nutrient": {
            "名称": "养分",
            "说明": "土壤养分含量",
            "单位": "mg/kg 或 %",
            "格式": "数值，如 25.5",
            "必填": "是"
          },
          "ph": {
            "名称": "pH值",
            "说明": "土壤酸碱度",
            "单位": "无量纲",
            "格式": "数值，0-14，如 6.5",
            "必填": "否"
          },
          "organic_matter": {
            "名称": "有机质",
            "说明": "有机质含量",
            "单位": "百分比 (%)",
            "格式": "数值，如 3.5",
            "必填": "否"
          },
          "soil_type": {
            "名称": "土壤类型",
            "说明": "土壤类型",
            "格式": "字符串，如 壤土",
            "必填": "否"
          },
          "depth": {
            "名称": "采样深度",
            "说明": "采样深度",
            "单位": "厘米 (cm)",
            "格式": "数值，如 20",
            "必填": "否"
          },
          "date": {
            "名称": "采样日期",
            "说明": "进行采样的日期",
            "格式": "YYYY-MM-DD，如 2026-03-13",
            "必填": "否"
          },
          "notes": {
            "名称": "备注",
            "说明": "其他补充说明信息",
            "格式": "自由文本",
            "必填": "否"
          }
        },
        "nutrient": 0.0,
        "ph": 0.0,
        "date": "YYYY-MM-DD",
        "notes": ""
      },
      "geometry": {
        "type": "Point",
        "coordinates": [
          116.397128,
          39.916527
        ]
      }
    }
  ],
  "_使用说明": {
    "1. 坐标系统": "使用 WGS84 坐标系 (EPSG:4326)，坐标格式为 [经度, 纬度]",
    "2. 经度范围": "-180 到 180 度",
    "3. 纬度范围": "-90 到 90 度",
    "4. 必填字段": "sample_id, 各行业主要字段, coordinates",
    "5. 示例坐标": "北京天安门 [116.397128, 39.916527]",
    "6. 数据格式": "标准 GeoJSON 格式，可直接导入系统",
    "7. 编码要求": "文件使用 UTF-8 编码",
    "8. 字段命名": "请勿修改 _ 开头的字段（保留字段）"
  }
}